.DS_Store
i2c_can/__init__.py
i2c_can/i2c_can.py
tests/__init__.py
tests/test_i2c_can.py
i2c_can-0.0.2.dist-info/LICENSE
i2c_can-0.0.2.dist-info/METADATA
i2c_can-0.0.2.dist-info/WHEEL
i2c_can-0.0.2.dist-info/entry_points.txt
i2c_can-0.0.2.dist-info/top_level.txt
i2c_can-0.0.2.dist-info/RECORD
