Metadata-Version: 2.1
Name: i2c_can
Version: 0.0.2
Summary: Library for Longan Labs I2C CAN Bus Module
Home-page: https://github.com/samskjord/ic2_can
Author: Sam Conway
Author-email: pypi@invertica.co.uk
Classifier: Programming Language :: Python :: 3
Classifier: License :: OSI Approved :: MIT License
Classifier: Operating System :: OS Independent
Requires-Python: >=3.6
License-File: LICENSE
Requires-Dist: smbus2
